sakura/__init__.py
sakura/client.py
sakura/db.py
sakura/sakura.py
sakura_fm-0.0.9.dist-info/LICENCE
sakura_fm-0.0.9.dist-info/METADATA
sakura_fm-0.0.9.dist-info/WHEEL
sakura_fm-0.0.9.dist-info/entry_points.txt
sakura_fm-0.0.9.dist-info/top_level.txt
sakura_fm-0.0.9.dist-info/RECORD
