Metadata-Version: 2.1
Name: sakura-fm
Version: 0.0.9
Summary: A simple scraper package for chatting with bots from sakura.fm
Home-page: https://github.com/awesome-Tofu/sakura_fm
Author: Aditya
Author-email: adityaraj6311@gmail.com
Keywords: sakura,sakura.fm,sakura scraper,sakurai
License-File: LICENCE
Requires-Dist: requests
Requires-Dist: beautifulsoup4
Requires-Dist: pymongo
